<?xml version="1.0"?>
<box>
  <height>1.0</height>
  <width>1.0</width>
  <depth>0.333333333</depth>
  <origin>
    <x>0.</x><y>0.</y><z>0.</z>
  </origin>
  <boundary>periodic</boundary>
  <regions>
    <region>
      <height>1.0</height>
      <width>1.0</width>
      <depth>0.333333333</depth>
      <exponent>10.0</exponent>
      <origin>
        <x>0.</x><y>0.</y><z>0.</z>
      </origin>
      <hydro>
        <rho>1.</rho>
        <vx>0.</vx>
        <vy>0.</vy>
        <vz>0.</vz>
        <p>3.+4.*log(2.)</p>
      </hydro>
    </region>
    <region>
      <height>0.8</height>
      <width>0.8</width>
      <depth>1.e9</depth>
      <exponent>2.0</exponent>
      <origin>
        <x>0.</x><y>0.</y><z>0.</z>
      </origin>
      <hydro>
        <rho>1.</rho>
        <vx>-(2.-5.*sqrt(x*x+y*y))*y/sqrt(x*x+y*y)</vx>
        <vy>(2.-5.*sqrt(x*x+y*y))*x/sqrt(x*x+y*y)</vy>
        <vz>0.</vz>
        <p>9.+12.5*(x*x+y*y)-20.*sqrt(x*x+y*y)+4.*log(sqrt(x*x+y*y)/0.2)</p>
      </hydro>
    </region>
    <region>
      <height>0.4</height>
      <width>0.4</width>
      <depth>1.e9</depth>
      <exponent>2.0</exponent>
      <origin>
        <x>0.</x><y>0.</y><z>0.</z>
      </origin>
      <hydro>
        <rho>1.</rho>
        <vx>-5.*y</vx>
        <vy>5.*x</vy>
        <vz>0.</vz>
        <p>5.+12.5*(x*x+y*y)</p>
      </hydro>
    </region>
  </regions>
</box>
